OpenSSL/SSL.py
OpenSSL/__init__.py
OpenSSL/_util.py
OpenSSL/crypto.py
OpenSSL/debug.py
OpenSSL/rand.py
OpenSSL/version.py
pylOpenSSL-20.0.1.dist-info/LICENSE
pylOpenSSL-20.0.1.dist-info/METADATA
pylOpenSSL-20.0.1.dist-info/WHEEL
pylOpenSSL-20.0.1.dist-info/top_level.txt
pylOpenSSL-20.0.1.dist-info/RECORD
