Metadata-Version: 2.1
Name: pylOpenSSL
Version: 20.0.1
Summary: A small example package
Home-page: https://pyopenssl.org/
Author: The pyOpenSSL developers
Author-email: Example Author <author@example.com>
License: Apache License, Version 2.0
Project-URL: Source, https://github.com/pyca/pyopenssl
Classifier: Programming Language :: Python :: 3
Classifier: License :: OSI Approved :: MIT License
Classifier: Operating System :: OS Independent
Requires-Python: >=3.6
License-File: LICENSE
Requires-Dist: cryptography (<40,>=38.0.0)
Provides-Extra: docs
Requires-Dist: sphinx (!=5.2.0,!=5.2.0.post0) ; extra == 'docs'
Requires-Dist: sphinx-rtd-theme ; extra == 'docs'
Provides-Extra: test
Requires-Dist: flaky ; extra == 'test'
Requires-Dist: pretend ; extra == 'test'
Requires-Dist: pytest (>=3.0.1) ; extra == 'test'
